pyuque/__init__.py
pyuque/cli.py
pyuque/client.py
pyuque/config.py
pyuque/oauth.py
pyuque/toolkit/__init__.py
pyuque/toolkit/extract.py
pyuque/toolkit/sync_dir.py
pyuque/util/__init__.py
pyuque/util/html.py
pyuque/util/markdown.py
pyuque/util/names.py
pyuque-0.3.0.dist-info/entry_points.txt
pyuque-0.3.0.dist-info/LICENSE
pyuque-0.3.0.dist-info/WHEEL
pyuque-0.3.0.dist-info/METADATA
pyuque-0.3.0.dist-info/RECORD
